fr_toolbelt/__init__.py
fr_toolbelt/__main__.py
fr_toolbelt/api_requests/__init__.py
fr_toolbelt/api_requests/get_documents.py
fr_toolbelt/preprocessing/__init__.py
fr_toolbelt/preprocessing/agencies.py
fr_toolbelt/preprocessing/dockets.py
fr_toolbelt/preprocessing/documents.py
fr_toolbelt/preprocessing/fields.py
fr_toolbelt/preprocessing/presidents.py
fr_toolbelt/preprocessing/rin.py
fr_toolbelt/utils/__init__.py
fr_toolbelt/utils/duplicates.py
fr_toolbelt/utils/format_dates.py
fr_toolbelt/utils/patch_progress.py
fr_toolbelt-0.2.0.dist-info/LICENSE
fr_toolbelt-0.2.0.dist-info/METADATA
fr_toolbelt-0.2.0.dist-info/WHEEL
fr_toolbelt-0.2.0.dist-info/top_level.txt
fr_toolbelt-0.2.0.dist-info/RECORD
