Metadata-Version: 2.2
Name: fr-toolbelt
Version: 0.2.0
Summary: Toolbelt of classes and functions written in Python to use with the Federal Register (FR) API.
Author-email: Mark Febrizio <mark.febrizio@gmail.com>
Maintainer-email: Mark Febrizio <mark.febrizio@gmail.com>
License: MIT License
Project-URL: Repository, https://github.com/mfebrizio/fr-toolbelt.git
Project-URL: Issues, https://github.com/mfebrizio/fr-toolbelt/issues
Keywords: Federal Register,government,api,regulation,regulatory
Classifier: Programming Language :: Python :: 3
Classifier: Programming Language :: Python :: 3.10
Classifier: Programming Language :: Python :: 3.11
Classifier: Programming Language :: Python :: 3.12
Classifier: Programming Language :: Python :: 3.13
Classifier: Programming Language :: Python :: 3 :: Only
Requires-Python: >=3.10
License-File: LICENSE
Requires-Dist: requests<3.0,>=2.31
Requires-Dist: progress<2.0,>=1.6
Requires-Dist: cursor<2.0,>=1.3
Provides-Extra: test
Requires-Dist: pytest<9.0,>=8.0; extra == "test"
